apiip/__init__.py
apiip-1.0.3.dist-info/METADATA
apiip-1.0.3.dist-info/WHEEL
apiip-1.0.3.dist-info/licenses/LICENCE
apiip-1.0.3.dist-info/RECORD
