Metadata-Version: 2.1
Name: apiip
Version: 1.0.3
Summary: Official python package for apiip.net, it offers one of the leading IP to geolocation API, get the location of any IP with a world-class API serving city, region, country, lat/long data, etc.
Project-URL: Homepage, https://apiip.net
Project-URL: Documentation, https://apiip.net/documentation
Author-email: apiip <apiipnet.business@gmail.com>
License-File: LICENCE
Classifier: License :: OSI Approved :: MIT License
Classifier: Programming Language :: Python :: 3
Requires-Python: >=3.0
